pyCoreOCR/__init__.py
pyCoreOCR/libCoreOCRLib.dylib
pycoreocr-0.3.0.dist-info/licenses/LICENSE
pycoreocr-0.3.0.dist-info/METADATA
pycoreocr-0.3.0.dist-info/WHEEL
pycoreocr-0.3.0.dist-info/top_level.txt
pycoreocr-0.3.0.dist-info/RECORD
