Metadata-Version: 2.4
Name: pyCoreOCR
Version: 0.3.0
Summary: Python wrapper for the LESIM-Co-Ltd/CoreOCR Swift library, enabling macOS Vision OCR from Python.
Author-email: "LESIM Co., Ltd." <s.kanagu@le-sim.com>
License-Expression: MIT
Project-URL: Homepage, https://github.com/LESIM-Co-Ltd/pyCoreOCR
Project-URL: Bug Tracker, https://github.com/LESIM-Co-Ltd/pyCoreOCR/issues
Project-URL: Source, https://github.com/LESIM-Co-Ltd/pyCoreOCR
Classifier: Programming Language :: Python :: 3
Classifier: Programming Language :: Python :: 3.8
Classifier: Programming Language :: Python :: 3.9
Classifier: Programming Language :: Python :: 3.10
Classifier: Programming Language :: Python :: 3.11
Classifier: Programming Language :: Python :: 3.12
Classifier: Operating System :: MacOS
Classifier: Intended Audience :: Developers
Classifier: Topic :: Software Development :: Libraries :: Python Modules
Classifier: Topic :: Text Processing :: General
Requires-Python: >=3.8
License-File: LICENSE
Dynamic: license-file
